rdf_sql_bulkloader/__init__.py
rdf_sql_bulkloader/cli.py
rdf_sql_bulkloader/loaders/__init__.py
rdf_sql_bulkloader/loaders/bulkloader.py
rdf_sql_bulkloader/loaders/sqlite3_bulkloader.py
rdf_sql_bulkloader-0.1.4.dist-info/METADATA
rdf_sql_bulkloader-0.1.4.dist-info/WHEEL
rdf_sql_bulkloader-0.1.4.dist-info/entry_points.txt
rdf_sql_bulkloader-0.1.4.dist-info/RECORD
