Metadata-Version: 2.1
Name: rdf-sql-bulkloader
Version: 0.1.4
Summary: rdf-sql-bulkloader
License: BSD 3
Author: Chris Mungall
Author-email: cjmungall@lbl.gov
Requires-Python: >=3.8,<4.0
Classifier: License :: Other/Proprietary License
Classifier: Programming Language :: Python :: 3
Classifier: Programming Language :: Python :: 3.8
Classifier: Programming Language :: Python :: 3.9
Classifier: Programming Language :: Python :: 3.10
Classifier: Programming Language :: Python :: 3.11
Provides-Extra: docs
Requires-Dist: click (>=8.1.3,<9.0.0)
Requires-Dist: curies
Requires-Dist: importlib (>=1.0.4,<2.0.0)
Requires-Dist: lightrdf (>=0.2.1,<0.3.0)
Requires-Dist: prefixmaps
Requires-Dist: pyoxigraph (>=0.3.6,<0.4.0)
Requires-Dist: setuptools (>=65.0.1,<66.0.0)
Requires-Dist: tox (>=3.25.1,<4.0.0)
